augmented_gpt/__init__.py
augmented_gpt/augmented_gpt.py
augmented_gpt/decorators.py
augmented_gpt/message.py
augmented_gpt/plugins/__init__.py
augmented_gpt/plugins/calc.py
augmented_gpt/plugins/memory.py
augmented_gpt/utils/__init__.py
augmented_gpt/utils/stt.py
augmented_gpt/utils/tts.py
augmented_gpt-0.3.0.dist-info/LICENSE
augmented_gpt-0.3.0.dist-info/METADATA
augmented_gpt-0.3.0.dist-info/WHEEL
augmented_gpt-0.3.0.dist-info/RECORD
